agentcore_rl_toolkit/__init__.py
agentcore_rl_toolkit/app.py
agentcore_rl_toolkit/reward_function.py
agentcore_rl_toolkit/frameworks/strands/__init__.py
agentcore_rl_toolkit/frameworks/strands/app.py
agentcore_rl_toolkit/frameworks/strands/rollout_collector.py
agentcore_rl_toolkit-0.1.0.dist-info/METADATA
agentcore_rl_toolkit-0.1.0.dist-info/WHEEL
agentcore_rl_toolkit-0.1.0.dist-info/licenses/LICENSE
agentcore_rl_toolkit-0.1.0.dist-info/licenses/NOTICE
agentcore_rl_toolkit-0.1.0.dist-info/RECORD
