Metadata-Version: 2.4
Name: agentcore-rl-toolkit
Version: 0.1.0
Summary: Toolkit for Seamlessly Enabling RL Training with Bedrock AgentCore.
Project-URL: Homepage, https://github.com/awslabs/agentcore-rl-toolkit
Author-email: Amazon Web Services - Labs <opensource@amazon.com>
License-Expression: Apache-2.0
License-File: LICENSE
License-File: NOTICE
Classifier: Development Status :: 3 - Alpha
Classifier: License :: OSI Approved :: Apache Software License
Classifier: Programming Language :: Python :: 3
Classifier: Programming Language :: Python :: 3.10
Classifier: Programming Language :: Python :: 3.11
Classifier: Programming Language :: Python :: 3.12
Classifier: Programming Language :: Python :: 3.13
Requires-Python: >=3.10
Requires-Dist: bedrock-agentcore-starter-toolkit<=0.2.0
Requires-Dist: bedrock-agentcore>=1.0.3
Requires-Dist: boto3>=1.40.55
Requires-Dist: python-dotenv>=1.0.0
Provides-Extra: dev
Requires-Dist: mypy>=1.0; extra == 'dev'
Requires-Dist: pre-commit>=3.0; extra == 'dev'
Requires-Dist: pytest>=7.0; extra == 'dev'
